socnet
