Metadata-Version: 2.1
Name: socnet
Version: 2.0.4
Summary: Social Network Model for COVID-19 infection
Home-page: https://github.com/diegomcarvalho/socnet
Author: Diego Carvalho
Author-email: d.carvalho@ieee.org
License: UNKNOWN
Download-URL: https://github.com/diegomcarvalho/socnet/archive/v2.0.4.tar.gz
Keywords: covid19,social network,complex network,net
Platform: UNKNOWN
Classifier: License :: OSI Approved :: MIT License
